nonebot_plugin_vits_tts/__init__.py
nonebot_plugin_vits_tts/config.py
nonebot_plugin_vits_tts/matcher.py
nonebot_plugin_vits_tts/rule.py
nonebot_plugin_vits_tts/utils/__init__.py
nonebot_plugin_vits_tts/utils/audio.py
nonebot_plugin_vits_tts/utils/lang_id.py
nonebot_plugin_vits_tts/utils/model.py
nonebot_plugin_vits_tts/vits/__init__.py
nonebot_plugin_vits_tts/vits/attentions.py
nonebot_plugin_vits_tts/vits/commons.py
nonebot_plugin_vits_tts/vits/language.py
nonebot_plugin_vits_tts/vits/models.py
nonebot_plugin_vits_tts/vits/modules.py
nonebot_plugin_vits_tts/vits/transforms.py
nonebot_plugin_vits_tts/vits/utils.py
nonebot_plugin_vits_tts/vits/voice.py
nonebot_plugin_vits_tts/vits/monotonic_align/__init__.py
nonebot_plugin_vits_tts/vits/monotonic_align/core.py
nonebot_plugin_vits_tts/vits/text/__init__.py
nonebot_plugin_vits_tts/vits/text/cantonese.py
nonebot_plugin_vits_tts/vits/text/cleaners.py
nonebot_plugin_vits_tts/vits/text/english.py
nonebot_plugin_vits_tts/vits/text/japanese.py
nonebot_plugin_vits_tts/vits/text/korean.py
nonebot_plugin_vits_tts/vits/text/mandarin.py
nonebot_plugin_vits_tts/vits/text/ngu_dialect.py
nonebot_plugin_vits_tts/vits/text/sanskrit.py
nonebot_plugin_vits_tts/vits/text/shanghainese.py
nonebot_plugin_vits_tts/vits/text/symbols.py
nonebot_plugin_vits_tts/vits/text/thai.py
nonebot_plugin_vits_tts-0.1.7.dist-info/LICENSE
nonebot_plugin_vits_tts-0.1.7.dist-info/METADATA
nonebot_plugin_vits_tts-0.1.7.dist-info/WHEEL
nonebot_plugin_vits_tts-0.1.7.dist-info/top_level.txt
nonebot_plugin_vits_tts-0.1.7.dist-info/RECORD
