Metadata-Version: 2.1
Name: nonebot_plugin_vits_tts
Version: 0.1.7
Summary: nonebot-plugin-vits-tts
Home-page: https://github.com/Redmomn/nonebot-plugin-vits-tts
Author: Redmomn
Author-email: 109732988+Redmomn@users.noreply.github.com
License: Apache-2.0
Keywords: nonebot2,vits,tts
License-File: LICENSE
Requires-Dist: torch
Requires-Dist: torchvision
Requires-Dist: torchaudio
Requires-Dist: numpy >=1.22.0
Requires-Dist: scipy
Requires-Dist: regex
Requires-Dist: cn2an
Requires-Dist: opencc
Requires-Dist: inflect
Requires-Dist: unidecode
Requires-Dist: eng-to-ipa
Requires-Dist: pyopenjtalk-prebuilt
Requires-Dist: jamo
Requires-Dist: ko-pron
Requires-Dist: pypinyin
Requires-Dist: jieba
Requires-Dist: indic-transliteration
Requires-Dist: num-thai
Requires-Dist: pydub
Requires-Dist: numba
Requires-Dist: tencentcloud-sdk-python-tmt
Requires-Dist: langdetect
Requires-Dist: nonebot-adapter-onebot >=2.0.0
Requires-Dist: nonebot2 >=2.0.0
